earthchem/__init__.py
earthchem/_version.py
earthchem/documentation.py
earthchem/geochem.py
earthchem/pagination.py
earthchem/query.py
earthchem/validation.py
earthchem/plot/__init__.py
earthchem/plot/geochron.py
earthchem/plot/spider.py
earthchem/plot/ternary.py
earthchem/resources/__init__.py
earthchem/resources/earthchem_rest_search_documentation.html
earthchem/resources/igneous_ontology.rdf+xml
earthchem/resources/soap_search_schema.xsd
earthchem/transform/__init__.py
earthchem/transform/additive.py
earthchem/transform/barycentric.py
earthchem/transform/centered.py
earthchem/transform/isometric.py
earthchem/transform/utilities.py
earthchem-0.0.5.dist-info/METADATA
earthchem-0.0.5.dist-info/RECORD
earthchem-0.0.5.dist-info/WHEEL
earthchem-0.0.5.dist-info/entry_points.txt
earthchem-0.0.5.dist-info/top_level.txt
