Metadata-Version: 2.1
Name: earthchem
Version: 0.0.5
Summary: Data slurper for getting stuff from Earthchem services
Home-page: https://github.com/jesserobertson/earthchem-pyclient.git
Author: Jess Robertson
Author-email: jesse.robertson@csiro.au
License: MIT
Project-URL: Test coverage, https://coveralls.io/github/jesserobertson/earthchem-pyclient
Project-URL: Test status, https://travis-ci.org/jesserobertson/earthchem-pyclient
Platform: UNKNOWN
Classifier: Development Status :: 3 - Alpha
Classifier: Intended Audience :: Developers
Classifier: Intended Audience :: Science/Research
Classifier: Natural Language :: English
Classifier: Operating System :: POSIX :: Linux
Classifier: Programming Language :: Python :: 3 :: Only
Classifier: Topic :: Internet
Classifier: Topic :: Scientific/Engineering
Classifier: Topic :: Software Development :: Libraries :: Python Modules
Provides-Extra: dev
Requires-Dist: geopandas
Requires-Dist: requests
Requires-Dist: beautifulsoup4
Requires-Dist: lxml
Requires-Dist: tqdm
Requires-Dist: python-ternary
Requires-Dist: periodictable
Requires-Dist: scikit-learn
Requires-Dist: scipy
Provides-Extra: dev
Requires-Dist: versioneer; extra == 'dev'
Requires-Dist: nbstripout; extra == 'dev'
Requires-Dist: nbdime; extra == 'dev'
